fshelper/__init__.py
fshelper/api.py
fshelper/endpoints.py
fshelper/errors.py
fshelper/models/__init__.py
fshelper/models/asset.py
fshelper/models/service_request.py
fshelper/support/__init__.py
fshelper/support/factories/__init__.py
fshelper/support/factories/asset.py
fshelper/v1/__init__.py
fshelper/v2/__init__.py
fshelper/v2/asset_types.py
fshelper/v2/assets.py
fshelper/v2/locations.py
fshelper/v2/service_items_endpoint.py
fshelper/v2/ticket_form_fields.py
fshelper/v2/tickets_endpoint.py
fshelper-0.3.0.dist-info/LICENSE
fshelper-0.3.0.dist-info/METADATA
fshelper-0.3.0.dist-info/WHEEL
fshelper-0.3.0.dist-info/top_level.txt
fshelper-0.3.0.dist-info/RECORD
