Metadata-Version: 2.1
Name: fshelper
Version: 0.3.0
Summary: Library for working with the FreshService API.
Author: Matthew Larsen
Author-email: matt.larsen@connorgp.com
License: MIT License
Project-URL: Source Code, https://github.com/matt-larsen-sld/freshservice-helper
Keywords: freshservice
Classifier: Development Status :: 2 - Pre-Alpha
Classifier: Programming Language :: Python :: 3
Classifier: License :: OSI Approved :: MIT License
Requires-Python: >=3.6
License-File: LICENSE
Requires-Dist: requests
Requires-Dist: pydantic-factories
